NodejsKaifaJiamiHuobi/README.md
NodejsKaifaJiamiHuobi/__init__.py
NodejsKaifaJiamiHuobi/__main__.py
NodejsKaifaJiamiHuobi/file.epub
NodejsKaifaJiamiHuobi/index.html
NodejsKaifaJiamiHuobi/css/__init__.py
NodejsKaifaJiamiHuobi/css/annotations.css
NodejsKaifaJiamiHuobi/css/main.css
NodejsKaifaJiamiHuobi/css/normalize.css
NodejsKaifaJiamiHuobi/css/popup.css
NodejsKaifaJiamiHuobi/font/__init__.py
NodejsKaifaJiamiHuobi/font/fontello.eot
NodejsKaifaJiamiHuobi/font/fontello.svg
NodejsKaifaJiamiHuobi/font/fontello.ttf
NodejsKaifaJiamiHuobi/font/fontello.woff
NodejsKaifaJiamiHuobi/img/__init__.py
NodejsKaifaJiamiHuobi/img/annotator-glyph-sprite.png
NodejsKaifaJiamiHuobi/img/annotator-icon-sprite.png
NodejsKaifaJiamiHuobi/img/apple-touch-icon.png
NodejsKaifaJiamiHuobi/img/cancelfullscreen.png
NodejsKaifaJiamiHuobi/img/close.png
NodejsKaifaJiamiHuobi/img/fullscreen.png
NodejsKaifaJiamiHuobi/img/loader.gif
NodejsKaifaJiamiHuobi/img/menu-icon.png
NodejsKaifaJiamiHuobi/img/save.png
NodejsKaifaJiamiHuobi/img/saved.png
NodejsKaifaJiamiHuobi/img/settings-s.png
NodejsKaifaJiamiHuobi/img/settings.png
NodejsKaifaJiamiHuobi/img/star.png
NodejsKaifaJiamiHuobi/js/__init__.py
NodejsKaifaJiamiHuobi/js/epub.js
NodejsKaifaJiamiHuobi/js/epub.min.js
NodejsKaifaJiamiHuobi/js/epub.min.map
NodejsKaifaJiamiHuobi/js/hooks.min.js
NodejsKaifaJiamiHuobi/js/hooks.min.map
NodejsKaifaJiamiHuobi/js/reader.js
NodejsKaifaJiamiHuobi/js/reader.js.map
NodejsKaifaJiamiHuobi/js/reader.min.js
NodejsKaifaJiamiHuobi/js/reader.min.map
NodejsKaifaJiamiHuobi/js/hooks/__init__.py
NodejsKaifaJiamiHuobi/js/hooks/extensions/__init__.py
NodejsKaifaJiamiHuobi/js/hooks/extensions/highlight.js
NodejsKaifaJiamiHuobi/js/libs/__init__.py
NodejsKaifaJiamiHuobi/js/libs/jquery.min.js
NodejsKaifaJiamiHuobi/js/libs/localforage.min.js
NodejsKaifaJiamiHuobi/js/libs/screenfull.js
NodejsKaifaJiamiHuobi/js/libs/screenfull.min.js
NodejsKaifaJiamiHuobi/js/libs/zip.min.js
NodejsKaifaJiamiHuobi/js/plugins/__init__.py
nodejs_kaifa_jiami_huobi-2024.3.1.0.dist-info/METADATA
nodejs_kaifa_jiami_huobi-2024.3.1.0.dist-info/WHEEL
nodejs_kaifa_jiami_huobi-2024.3.1.0.dist-info/entry_points.txt
nodejs_kaifa_jiami_huobi-2024.3.1.0.dist-info/top_level.txt
nodejs_kaifa_jiami_huobi-2024.3.1.0.dist-info/RECORD
